Workbook

Sheet Pivot Tables
E3: Location/Cluster | F3: Count of Location/Cluster | H3: Question Type | I3: Count of Question Type | K3: Repeat Question (Yes/No) | L3: Count of Repeat Question (Yes/No)
E4: MIDC | F4: 52 | H4: Documents | I4: 39 | K4: No | L4: 37
E5: Mumbai Central | F5: 47 | H5: Holiday | I5: 1 | K5: (blank)
E6: (blank) | H6: Information | I6: 33 | K6: Yes | L6: 59
E7: Grand Total | F7: 99 | H7: (blank) | K7: Grand Total | L7: 96
H8: Grievance | I8: 26
H9: Grand Total | I9: 99 | K9: Notes Language | L9: Count of Notes Language
E10: Department (HR/Admin or Helpdesk) | F10: Count of Department (HR/Admin or Helpdesk) | K10: Hindi | L10: 64
E11: Helpdesk | F11: 57 | H11: Status | I11: Count of Status | K11: Marathi | L11: 35
E12: HR/Admin | F12: 18 | H12: Solved | I12: 78 | K12: (blank)
E13: (blank) | H13: (blank) | K13: Grand Total | L13: 99
E14: Production | F14: 23 | H14: Pending | I14: 21
E15: Others | F15: 1 | H15: Grand Total | I15: 99
E16: Grand Total | F16: 99

Sheet Dashboard

Sheet V2V
A1: Sr. No. | B1: Code | C1: Worker Name | D1: Employee Code | E1: Voice Note Received- date | F1: Location/Cluster | G1: Department (HR/Admin or Helpdesk) | H1: Question Type | I1: Department Spoc | J1: Date Sent to Department | K1: Notes Language | L1: Response Received Date | M1: Sent Back to Worker (Yes/No) | N1: Status | O1: Repeat Question (Yes/No) | P1: Remarks
A2: 1 | B2: HR_Ad_Q_1 | C2: Anjumbanu Salman Khan | D2: =VLOOKUP(C2,Workers!B:C,2) -> 508 | E2: 46041 | F2: Mumbai Central | G2: HR/Admin | H2: Holiday | I2: Grishma | J2: 46041 | K2: Hindi | L2: 46041 | M2: Yes | N2: Solved | O2: No
A3: 2 | B3: Hd_Q_1 | C3: Divya Sagar Pali | D3: =VLOOKUP(C3,Workers!B:C,2) -> 575 | E3: 46041 | F3: Mumbai Central | G3: Helpdesk | H3: Documents | I3: Dinesh | J3: 46042 | K3: Hindi | L3: 46042 | M3: Yes | N3: Solved | O3: No
A4: 3 | B4: Hd_Q_3 | C4: Hema Laxman Tele | D4: =VLOOKUP(C4,Workers!B:C,2) -> 23 | E4: 46042 | F4: MIDC | G4: Helpdesk | H4: Documents | I4: Priti | J4: 46042 | K4: Marathi | L4: 46042 | M4: Yes | N4: Solved | O4: No
A5: 4 | B5: Hd_Q_2 | C5: Karuna Krishna Gawade | D5: =VLOOKUP(C5,Workers!B:C,2) -> 32 | E5: 46042 | F5: MIDC | G5: Helpdesk | H5: Documents | I5: Priti | J5: 46042 | K5: Marathi | L5: 46042 | M5: Yes | N5: Solved | O5: No
A6: 5 | B6: Hd_Q_4 | C6: Seema Shambhu Bidlan | D6: =VLOOKUP(C6,Workers!B:C,2) -> 92 | E6: 46042 | F6: MIDC | G6: Helpdesk | H6: Documents | I6: Priti | J6: 46042 | K6: Hindi | L6: 46042 | M6: Yes | N6: Solved | O6: No
A7: 6 | B7: Hd_Q_5 | C7: Chanda Devi | D7: =VLOOKUP(C7,Workers!B:C,2) -> 12 | E7: 46042 | F7: MIDC | G7: Helpdesk | H7: Documents | I7: Priti | J7: 46042 | K7: Hindi | L7: 46042 | M7: Yes | N7: Solved | O7: No
A8: 7 | B8: Hd_Q_6 | C8: Sarika Anil Kamble | D8: =VLOOKUP(C8,Workers!B:C,2) -> 89 | E8: 46042 | F8: MIDC | G8: Helpdesk | H8: Information | I8: Priti | J8: 46042 | K8: Marathi | L8: 46042 | M8: Yes | N8: Solved | O8: No
A9: 8 | B9: Hd_Q_8 | C9: Seema Shambhu Bidlan | D9: =VLOOKUP(C9,Workers!B:C,2) -> 92 | E9: 46042 | F9: MIDC | G9: Helpdesk | H9: Information | I9: Priti | J9: 46042 | K9: Hindi | L9: 46043 | M9: Yes | N9: Solved | O9: No | P9: Follow up
A10: 9 | B10: Hd_Q_7 | C10: Sanchita Sujindra Ayake | D10: =VLOOKUP(C10,Workers!B:C,2) -> 85 | E10: 46043 | F10: MIDC | G10: Helpdesk | H10: Documents | I10: Priti | J10: 46043 | K10: Marathi | L10: 46043 | M10: Yes | N10: Solved | O10: No
A11: 10 | B11: Hd_Q_9 | C11: Leena Khandu Garud | D11: =VLOOKUP(C11,Workers!B:C,2) -> 39 | E11: 46043 | F11: MIDC | G11: Helpdesk | H11: Documents | I11: Priti | J11: 46043 | K11: Marathi | L11: 46043 | M11: Yes | N11: Solved | O11: No
A12: 11 | B12: Hd_Q_10 | C12: Nirmala Rammilan Prajapati | D12: =VLOOKUP(C12,Workers!B:C,2) -> 238 | E12: 46043 | F12: MIDC | G12: Helpdesk | H12: Information | I12: Priti | J12: 46043 | K12: Hindi | L12: 46043 | M12: Yes | N12: Solved | O12: No
A13: 12 | B13: Hd_Q_11 | C13: Sandhya Sanjay Pawar | D13: =VLOOKUP(C13,Workers!B:C,2) -> 214 | E13: 46043 | F13: MIDC | G13: Helpdesk | H13: Documents | I13: Priti | J13: 46043 | K13: Marathi | L13: 46043 | M13: Yes | N13: Solved | O13: No
A14: 13 | B14: Hd_Q_12 | C14: Pramila Bhagwan Jadhav | D14: =VLOOKUP(C14,Workers!B:C,2) -> 61 | E14: 46043 | F14: MIDC | G14: Helpdesk | H14: Documents | I14: Priti | J14: 46043 | K14: Marathi | L14: 46043 | M14: Yes | N14: Solved | O14: No
A15: 14 | B15: Hd_Q_13 | C15: Beby Navsha Baraf | D15: =VLOOKUP(C15,Workers!B:C,2) -> 10 | E15: 46043 | F15: MIDC | G15: Helpdesk | H15: Information | I15: Priti | J15: 46043 | K15: Marathi | L15: 46043 | M15: Yes | N15: Solved | O15: No
A16: 15 | B16: Hd_Q_14 | C16: Varsha Pappu Kirkire | D16: =VLOOKUP(C16,Workers!B:C,2) -> 116 | E16: 46043 | F16: MIDC | G16: Helpdesk | H16: Information | I16: Priti | J16: 46043 | K16: Marathi | L16: 46043 | M16: Yes | N16: Solved | O16: Yes | P16: Aadhar delivery
A17: 16 | B17: Hd_Q_16 | C17: Vidya Sunil Magare | D17: =VLOOKUP(C17,Workers!B:C,2) -> 135 | E17: 46043 | F17: MIDC | G17: Helpdesk | H17: Documents | I17: Priti | J17: 46043 | K17: Marathi | L17: 46043 | M17: Yes | N17: Solved | O17: Yes | P17: Scholarship
A18: 17 | B18: Hd_Q_15 | C18: Lata Bapu Patil | D18: =VLOOKUP(C18,Workers!B:C,2) -> 37 | E18: 46043 | F18: MIDC | G18: Helpdesk | H18: Documents | I18: Priti | J18: 46043 | K18: Marathi | L18: 46043 | M18: Yes | N18: Solved | O18: No | P18: Post office saving account
A19: 18 | B19: Hd_Q_17 | C19: Sarika Anil Kamble | D19: =VLOOKUP(C19,Workers!B:C,2) -> 89 | E19: 46043 | F19: MIDC | G19: Helpdesk | H19: Documents | I19: Priti | J19: 46043 | K19: Marathi | L19: 46043 | M19: Yes | N19: Solved | O19: No | P19: PPF
A20: 19 | B20: Hd_Q_18 | C20: Krutika Kishore Saware | D20: =VLOOKUP(C20,Workers!B:C,2) -> 35 | E20: 46043 | F20: MIDC | G20: Helpdesk | H20: Information | I20: Priti | J20: 46043 | K20: Marathi | L20: 46043 | M20: Yes | N20: Solved | O20: No | P20: Sukhanya Account
A21: 20 | B21: Hd_Q_19 | C21: Indravati Devi Sunil Kumar Jaiswal | D21: =VLOOKUP(C21,Workers!B:C,2) -> 24 | E21: 46043 | F21: MIDC | G21: Helpdesk | H21: Information | I21: Priti | J21: 46043 | K21: Hindi | L21: 46043 | M21: Yes | N21: Solved | O21: No | P21: Policy info
A22: 21 | B22: HR_Ad_Q_2 | C22: Shakti Suresh Pardeshi | D22: =VLOOKUP(C22,Workers!B:C,2) -> 533 | E22: 46044 | F22: Mumbai Central | G22: HR/Admin | H22: Grievance | I22: Grishma | J22: 46044 | K22: Hindi | L22: 46044 | M22: Yes | N22: Solved | O22: No | P22: Compliance
A23: 22 | B23: HR_Ad_Q_4 | C23: Hadiqa Jabir Shaikh | D23: =VLOOKUP(C23,Workers!B:C,2) -> 565 | E23: 46044 | F23: Mumbai Central | G23: HR/Admin | H23: Information | I23: Veena | J23: 46044 | K23: Hindi | L23: 46045 | M23: Yes | N23: Solved | O23: Yes | P23: PF Amount
A24: 23 | C24: Rehana Mubeen Sayed | D24: =VLOOKUP(C24,Workers!B:C,2) -> 522 | E24: 46044 | F24: Mumbai Central | G24: HR/Admin | H24: Information | I24: Veena | J24: 46044 | K24: Hindi | N24: Pending | P24: Holiday Detail
A25: 24 | B25: NG_Q_1 | C25: Dhanraj Suresh Pardeshi | D25: =VLOOKUP(C25,Workers!B:C,2) -> 512 | E25: 46044 | F25: Mumbai Central | G25: Others | H25: Grievance | J25: 46044 | K25: Hindi | N25: Pending | P25: Nextgen
A26: 25 | B26: Hd_Q_20 | C26: T Bama | D26: =VLOOKUP(C26,Workers!B:C,2) -> 110 | E26: 46044 | F26: MIDC | G26: Helpdesk | H26: Documents | I26: Priti | J26: 46044 | K26: Hindi | L26: 46044 | M26: Yes | N26: Solved | O26: No | P26: Name Change
A27: 26 | B27: Hd_Q_21 | C27: Kalaiyrashi Murgeshan Nadar | D27: =VLOOKUP(C27,Workers!B:C,2) -> 29 | E27: 46044 | F27: MIDC | G27: Helpdesk | H27: Documents | I27: Priti | J27: 46044 | K27: Hindi | L27: 46044 | M27: Yes | N27: Solved | O27: No | P27: Ayushman Card
A28: 27 | B28: HR_Ad_Q_5 | C28: Hemlata Avinash Pardeshi | D28: =VLOOKUP(C28,Workers!B:C,2) -> 513 | E28: 46044 | F28: Mumbai Central | G28: HR/Admin | H28: Information | I28: Veena | J28: 46044 | K28: Hindi | L28: 46045 | M28: Yes | N28: Solved | O28: Yes | P28: PF Amount
A29: 28 | B29: Hd_Q_23 | C29: Shila Rahul Sadaphule | D29: =VLOOKUP(C29,Workers!B:C,2) -> 95 | E29: 46044 | F29: MIDC | G29: Helpdesk | H29: Documents | I29: Priti | J29: 46044 | K29: Marathi | L29: 46044 | M29: Yes | N29: Solved | O29: Yes | P29: Aadhar delivery
A30: 29 | B30: Hd_Q_22 | C30: Nikita Ishwar Mahale | D30: =VLOOKUP(C30,Workers!B:C,2) -> 216 | E30: 46044 | F30: MIDC | G30: Helpdesk | H30: Documents | I30: Priti | J30: 46044 | K30: Marathi | L30: 46044 | M30: Yes | N30: Solved | O30: Yes | P30: Ration Card Name Update
A31: 30 | B31: Hd_Q_24 | C31: Rupali Pritesh Mirke | D31: =VLOOKUP(C31,Workers!B:C,2) -> 244 | E31: 46044 | F31: MIDC | G31: Helpdesk | H31: Documents | I31: Priti | J31: 46044 | K31: Marathi | L31: 46044 | M31: Yes | N31: Solved | O31: Yes | P31: Ayushman Card
A32: 31 | B32: P_Q_1 | C32: Babita Vilas Pardeshi | D32: =VLOOKUP(C32,Workers!B:C,2) -> 562 | E32: 46044 | F32: Mumbai Central | G32: Production | H32: Information | I32: Manjiri | J32: 46044 | K32: Hindi | L32: 46045 | M32: Yes | N32: Solved | O32: No | P32: Payment
A33: 32 | B33: HR_Ad_Q_6 | C33: Babita Vilas Pardeshi | D33: =VLOOKUP(C33,Workers!B:C,2) -> 562 | E33: 46044 | F33: Mumbai Central | G33: HR/Admin | H33: Information | I33: Veena | J33: 46044 | K33: Hindi | L33: 46045 | M33: Yes | N33: Solved | O33: Yes | P33: PF Amount
A34: 33 | B34: Hd_Q_25 | C34: Rekha Akash Pardeshi | D34: =VLOOKUP(C34,Workers!B:C,2) -> 523 | E34: 46044 | F34: Mumbai Central | G34: Helpdesk | H34: Information | I34: Dinesh | J34: 46044 | K34: Hindi | L34: 46044 | M34: Yes | N34: Solved | O34: Yes | P34: Ration Card Income Update
A35: 34 | B35: HR_Ad_Q_7 | C35: Sunaina Kalidas Pardeshi | D35: =VLOOKUP(C35,Workers!B:C,2) -> 561 | E35: 46044 | F35: Mumbai Central | G35: HR/Admin | H35: Information | I35: Veena | J35: 46045 | K35: Hindi | L35: 46045 | M35: Yes | N35: Solved | O35: Yes | P35: PF Amount
A36: 35 | C36: Madhuri Shesnarayan Tiwari | D36: =VLOOKUP(C36,Workers!B:C,2) -> 552 | E36: 46045 | F36: Mumbai Central | G36: HR/Admin | H36: Grievance | I36: Veena | J36: 46045 | K36: Hindi | N36: Pending | P36: Locker Issue
A37: 36 | B37: Hd_Q_29 | C37: Vandana Ranjeet Pardeshi | D37: =VLOOKUP(C37,Workers!B:C,2) -> 545 | E37: 46045 | F37: Mumbai Central | G37: Helpdesk | H37: Documents | I37: Dinesh | J37: 46045 | K37: Hindi | L37: 46046 | M37: Yes | N37: Solved | O37: Yes | P37: Ration Card Name Update
A38: 37 | C38: Bharti Vikram Pardeshi | D38: =VLOOKUP(C38,Workers!B:C,2) -> 511 | E38: 46045 | F38: Mumbai Central | G38: HR/Admin | H38: Information | I38: Bharati | J38: 46045 | K38: Hindi | N38: Pending | O38: Yes | P38: Holiday Detail
A39: 38 | B39: P_Q_2 | C39: Bharti Vikram Pardeshi | D39: =VLOOKUP(C39,Workers!B:C,2) -> 511 | E39: 46045 | F39: Mumbai Central | G39: Production | H39: Information | I39: Manjiri | J39: 46045 | K39: Hindi | L39: 46051 | M39: Yes | N39: Solved | O39: No | P39: Production Piece Details
A40: 39 | B40: HR_Ad_Q_3 | C40: Jyoti Danraj Pardeshi | D40: =VLOOKUP(C40,Workers!B:C,2) -> 587 | E40: 46045 | F40: Mumbai Central | G40: HR/Admin | H40: Information | I40: Veena | J40: 46045 | K40: Hindi | L40: 46045 | M40: Yes | N40: Solved | O40: Yes | P40: PF Amount
A41: 40 | B41: Hd_Q_26 | C41: Sahista Habibul Khan | D41: =VLOOKUP(C41,Workers!B:C,2) -> 84 | E41: 46045 | F41: MIDC | G41: Helpdesk | H41: Documents | I41: Priti | J41: 46045 | K41: Marathi | L41: 46045 | M41: Yes | N41: Solved | O41: Yes | P41: Ayushman Card
A42: 41 | B42: Hd_Q_27 | C42: Shahanaz Sultan Baba | D42: =VLOOKUP(C42,Workers!B:C,2) -> 94 | E42: 46045 | F42: MIDC | G42: Helpdesk | H42: Information | I42: Priti | J42: 46046 | K42: Marathi | L42: 46046 | M42: Yes | N42: Solved | O42: No | P42: Loan
A43: 42 | B43: Hd_Q_28 | C43: Bhavana Nitin Pardeshi | D43: =VLOOKUP(C43,Workers!B:C,2) -> 546 | E43: 46046 | F43: Mumbai Central | G43: Helpdesk | H43: Documents | I43: Dinesh | J43: 46046 | K43: Hindi | L43: 46046 | M43: Yes | N43: Solved | O43: Yes | P43: Ration Card Update & PF Amount
A44: 43 | B44: Hd_Q_30 | C44: Sandhya Sanjay Pawar | D44: =VLOOKUP(C44,Workers!B:C,2) -> 214 | E44: 46046 | F44: MIDC | G44: Helpdesk | H44: Documents | I44: Priti | J44: 46046 | K44: Marathi | L44: 46049 | M44: Yes | N44: Solved | O44: No | P44: RD
A45: 44 | B45: Hd_Q_31 | C45: Sangeeta Babal Nadage | D45: =VLOOKUP(C45,Workers!B:C,2) -> 223 | E45: 46046 | F45: MIDC | G45: Helpdesk | H45: Documents | I45: Priti | J45: 46046 | K45: Marathi | L45: 46049 | M45: Yes | N45: Solved | O45: Yes | P45: Aadhar delivery
A46: 45 | B46: Hd_Q_34 | C46: Nikita Ishwar Mahale | D46: =VLOOKUP(C46,Workers!B:C,2) -> 216 | E46: 46046 | F46: MIDC | G46: Helpdesk | H46: Documents | I46: Priti | J46: 46046 | K46: Marathi | L46: 46049 | M46: Yes | N46: Solved | O46: No | P46: Marriage Certificate
A47: 46 | B47: Hd_Q_33 | C47: Neelam Nitesh Mirke | D47: =VLOOKUP(C47,Workers!B:C,2) -> 245 | E47: 46046 | F47: MIDC | G47: Helpdesk | H47: Documents | I47: Priti | J47: 46046 | K47: Marathi | L47: 46049 | M47: Yes | N47: Solved | O47: Yes | P47: Ration Card Name Update
A48: 47 | B48: Hd_Q_35 | C48: Kalpana Nandu Lotade | D48: =VLOOKUP(C48,Workers!B:C,2) -> 220 | E48: 46046 | F48: MIDC | G48: Helpdesk | H48: Documents | I48: Priti | J48: 46046 | K48: Marathi | L48: 46049 | M48: Yes | N48: Solved | O48: Yes | P48: Marriage Certificate
A49: 48 | B49: Hd_Q_32 | C49: Gudmesh Kumar | D49: =VLOOKUP(C49,Workers!B:C,2) -> 235 | E49: 46046 | F49: MIDC | G49: Helpdesk | H49: Documents | I49: Priti | J49: 46046 | K49: Hindi | L49: 46049 | M49: Yes | N49: Solved | O49: Yes | P49: Ayushman Card
A50: 49 | B50: Hd_Q_36 | C50: Arpana Alpesh Pawar | D50: =VLOOKUP(C50,Workers!B:C,2) -> 6 | E50: 46047 | F50: MIDC | G50: Helpdesk | H50: Information | I50: Priti | J50: 46049 | K50: Marathi | L50: 46049 | M50: Yes | N50: Solved | O50: No | P50: Sarthi App
... A76: 75 | B76: Hd_Q_53 | C76: Sarika Anil Kamble | D76: =VLOOKUP(C76,Workers!B:C,2) -> 89 | E76: 46055 | F76: MIDC | G76: Helpdesk | H76: Documents | I76: Priti | J76: 46055 | K76: Hindi | L76: 46057 | M76: Yes | N76: Solved | O76: Yes | P76: Ration Card Update
A77: 76 | C77: Sunil Nanka Bethwala | D77: =VLOOKUP(C77,Workers!B:C,2) -> 559 | E77: 46056 | F77: Mumbai Central | G77: Production | H77: Grievance | I77: Manjiri | J77: 46056 | K77: Hindi | N77: Pending | O77: No | P77: Production
A78: 77 | B78: HR_Ad_Q_12 | C78: Bharti Vikram Pardeshi | D78: =VLOOKUP(C78,Workers!B:C,2) -> 511 | E78: 46056 | F78: Mumbai Central | G78: HR/Admin | H78: Information | I78: Veena | J78: 46056 | K78: Hindi | L78: 46057 | M78: Yes | N78: Solved | O78: Yes | P78: Loan | Q78: HR_Ad_Q_12.1
A79: 78 | B79: Hd_Q_55 | C79: Vatsala Avinash Bamane | D79: =VLOOKUP(C79,Workers!B:C,2) -> 577 | E79: 46057 | F79: Mumbai Central | G79: Helpdesk | H79: Documents | I79: Dinesh | J79: 46057 | K79: Hindi | L79: 46057 | M79: Yes | N79: Solved | O79: Yes | P79: Ayushman Card
A80: 79 | B80: Hd_Q_56 | C80: Hadiqa Jabir Shaikh | D80: =VLOOKUP(C80,Workers!B:C,2) -> 565 | E80: 46057 | F80: Mumbai Central | G80: Helpdesk | H80: Documents | I80: Dinesh | J80: 46057 | K80: Hindi | L80: 46057 | M80: Yes | N80: Solved | O80: Yes | P80: Aadhar delivery
A81: 80 | B81: HR_Ad_Q_14 | C81: Rekha Akash Pardeshi | D81: =VLOOKUP(C81,Workers!B:C,2) -> 523 | E81: 46057 | F81: Mumbai Central | G81: HR/Admin | H81: Grievance | I81: Veena | J81: 46057 | K81: Hindi | L81: 46058 | M81: Yes | N81: Solved | O81: No | P81: Floor Issue
A82: 81 | B82: P_Q_7 | C82: Sanchita Sujindra Ayake | D82: =VLOOKUP(C82,Workers!B:C,2) -> 85 | E82: 46057 | F82: MIDC | G82: Production | H82: Grievance | I82: Manjiri | J82: 46057 | K82: Hindi | L82: 46058 | M82: Yes | N82: Solved | O82: Yes | P82: Production
A83: 82 | B83: P_Q_8 | C83: Dhanraj Suresh Pardeshi | D83: =VLOOKUP(C83,Workers!B:C,2) -> 512 | E83: 46057 | F83: Mumbai Central | G83: Production | H83: Grievance | I83: Manjiri | J83: 46057 | K83: Hindi | L83: 46058 | M83: Yes | N83: Solved | O83: Yes | P83: Production | Q83: P_Q_8.1
A84: 83 | B84: P_Q_9 | C84: Nandini Ashok Pardeshi | D84: =VLOOKUP(C84,Workers!B:C,2) -> 601 | E84: 46057 | F84: Mumbai Central | G84: Production | H84: Grievance | I84: Manjiri | J84: 46057 | K84: Hindi | L84: 46058 | M84: Yes | N84: Pending | O84: Yes | P84: Production
A85: 84 | B85: P_Q_10 | C85: Hadiqa Jabir Shaikh | D85: =VLOOKUP(C85,Workers!B:C,2) -> 565 | E85: 46058 | F85: Mumbai Central | G85: Production | H85: Grievance | I85: Manjiri | J85: 46058 | K85: Hindi | L85: 46058 | M85: Yes | N85: Solved | O85: Yes | P85: Production
A86: 85 | B86: Hd_Q_57 | C86: Anjumbanu Salman Khan | D86: =VLOOKUP(C86,Workers!B:C,2) -> 508 | E86: 46058 | F86: Mumbai Central | G86: Helpdesk | H86: Documents | I86: Dinesh | J86: 46058 | K86: Hindi | L86: 46058 | M86: Yes | N86: Solved | O86: No | P86: Address Change | Q86: Hd_Q_57.1
A87: 86 | B87: P_Q_10 | C87: Anjumbanu Salman Khan | D87: =VLOOKUP(C87,Workers!B:C,2) -> 508 | E87: 46058 | F87: Mumbai Central | G87: Production | H87: Grievance | I87: Manjiri | J87: 46058 | K87: Hindi | L87: 46058 | M87: Yes | N87: Solved | O87: Yes | P87: Production | Q87: Same
A88: 87 | B88: P_Q_10 | C88: Shakti Suresh Pardeshi | D88: =VLOOKUP(C88,Workers!B:C,2) -> 533 | E88: 46058 | F88: Mumbai Central | G88: Production | H88: Grievance | I88: Manjiri | J88: 46058 | K88: Hindi | L88: 46058 | M88: Yes | N88: Solved | O88: Yes | P88: Production | Q88: Same
A89: 88 | B89: P_Q_10 | C89: Pritam Suresh Pardeshi | D89: =VLOOKUP(C89,Workers!B:C,2) -> 595 | E89: 46058 | F89: Mumbai Central | G89: Production | H89: Grievance | I89: Rakesh | J89: 46058 | K89: Hindi | L89: 46058 | M89: Yes | N89: Solved | O89: Yes | P89: Production
A90: 89 | B90: HR_Ad_Q_15 | C90: Shakti Suresh Pardeshi | D90: =VLOOKUP(C90,Workers!B:C,2) -> 533 | E90: 46058 | F90: Mumbai Central | G90: Production | H90: Grievance | I90: Veena | J90: 46058 | K90: Hindi | L90: 46058 | M90: Yes | N90: Solved | O90: Yes | P90: Floor Issue
A91: 90 | B91: P_Q_10 | C91: Pritam Suresh Pardeshi | D91: =VLOOKUP(C91,Workers!B:C,2) -> 595 | E91: 46058 | F91: Mumbai Central | G91: HR/Admin | H91: Grievance | I91: Veena | J91: 46058 | K91: Hindi | N91: Pending | O91: Yes | P91: Production
A92: 91 | B92: P_Q_10 | C92: Anjumbanu Salman Khan | D92: =VLOOKUP(C92,Workers!B:C,2) -> 508 | E92: 46058 | F92: Mumbai Central | G92: Production | H92: Grievance | I92: Rakesh | J92: 46058 | K92: Hindi | N92: Pending | O92: Yes | P92: Production
A93: 92 | B93: P_Q_10 | C93: Ayyub Mehboob Khan | D93: =VLOOKUP(C93,Workers!B:C,2) -> 507 | E93: 46058 | F93: Mumbai Central | G93: Production | H93: Grievance | I93: Manjiri | J93: 46058 | K93: Hindi | N93: Pending | O93: Yes | P93: Production
A94: 93 | B94: P_Q_10 | C94: Ayyub Mehboob Khan | D94: =VLOOKUP(C94,Workers!B:C,2) -> 507 | E94: 46058 | F94: Mumbai Central | G94: Production | H94: Grievance | I94: Rakesh | J94: 46058 | K94: Hindi | N94: Pending | O94: Yes | P94: Production
A95: 94 | C95: Sneha Babasaheb Misal | D95: =VLOOKUP(C95,Workers!B:C,2) -> 217 | E95: 46058 | F95: MIDC | G95: Helpdesk | H95: Information | I95: Dinesh | J95: 46058 | K95: Marathi | N95: Pending | O95: Yes | P95: Next gen
A96: 95 | B96: P_Q_10 | C96: Nazim Ali Tahir Ali Khan | D96: =VLOOKUP(C96,Workers!B:C,2) -> 517 | E96: 46058 | F96: Mumbai Central | G96: Production | H96: Grievance | I96: Rakesh | J96: 46058 | K96: Hindi | N96: Pending | O96: Yes | P96: Production
A97: 96 | B97: P_Q_10 | C97: Nazim Ali Tahir Ali Khan | D97: =VLOOKUP(C97,Workers!B:C,2) -> 517 | E97: 46058 | F97: Mumbai Central | G97: Production | H97: Grievance | I97: Manjiri | J97: 46058 | K97: Hindi | N97: Pending | O97: Yes | P97: Production
A98: 97 | B98: P_Q_10 | C98: Yasmin Ayub Khan | D98: =VLOOKUP(C98,Workers!B:C,2) -> 540 | E98: 46058 | F98: Mumbai Central | G98: Production | H98: Grievance | I98: Rakesh | J98: 46058 | K98: Hindi | N98: Pending | O98: Yes | P98: Production
A99: 98 | B99: P_Q_10 | C99: Yasmin Ayub Khan | D99: =VLOOKUP(C99,Workers!B:C,2) -> 540 | E99: 46058 | F99: Mumbai Central | G99: Production | H99: Grievance | I99: Manjiri | J99: 46058 | K99: Hindi | N99: Pending | O99: Yes | P99: Production
A100: 99 | B100: P_Q_10 | C100: Rehana Mubeen Sayed | D100: =VLOOKUP(C100,Workers!B:C,2) -> 522 | E100: 46058 | F100: Mumbai Central | G100: Production | H100: Grievance | I100: Rakesh | J100: 46058 | K100: Hindi | N100: Pending | O100: Yes | P100: Production
A101: 100 | B101: HR_Ad_Q_16 | C101: Zulekha Rouf Ansari | D101: =VLOOKUP(C101,Workers!B:C,2) -> 541 | E101: 46058 | F101: Mumbai Central | G101: HR/Admin | H101: Grievance | I101: Veena | J101: 46058 | K101: Hindi | L101: 46058 | M101: Yes | N101: Solved | O101: Yes | P101: Floor Issue
A102: 101 | B102: HR_Ad_Q_16 | C102: Zulekha Rouf Ansari | D102: =VLOOKUP(C102,Workers!B:C,2) -> 541 | E102: 46058 | F102: Mumbai Central | G102: HR/Admin | H102: Grievance | I102: Aloysia | J102: 46058 | K102: Hindi | N102: Pending | O102: Yes | P102: Floor Issue
A103: 102 | B103: Hd_Q_60 | C103: Sahista Habibul Khan | D103: =VLOOKUP(C103,Workers!B:C,2) -> 84 | E103: 46058 | F103: MIDC | G103: Helpdesk | H103: Documents | I103: Priti | J103: 46058 | K103: Hindi | L103: 46058 | M103: Yes | N103: Solved | O103: Yes | P103: Ayushman Card
A104: 103 | B104: Hd_Q_58 | C104: Seema Ganesh Pardeshi | D104: =VLOOKUP(C104,Workers!B:C,2) -> 531 | E104: 46058 | F104: Mumbai Central | G104: Helpdesk | H104: Documents | I104: Dinesh | J104: 46058 | K104: Hindi | L104: 46058 | M104: Yes | N104: Solved | O104: Yes | P104: Scheme Enrollment
A105: 104 | B105: Hd_Q_59 | C105: Shahanaz Sultan Baba | D105: =VLOOKUP(C105,Workers!B:C,2) -> 94 | E105: 46058 | F105: MIDC | G105: Helpdesk | H105: Documents | I105: Priti | J105: 46058 | K105: Marathi | L105: 46058 | M105: Yes | N105: Solved | O105: Yes | P105: Loan
A106: 105 | C106: Bharti Vikram Pardeshi | D106: =VLOOKUP(C106,Workers!B:C,2) -> 511 | E106: 46058 | F106: Mumbai Central | G106: Production | H106: Information | I106: Bharti | J106: 46058 | K106: Hindi | N106: Pending | O106: Yes | P106: Per Piece Amount
A107: 106 | C107: Seema Shambhu Bidlan | D107: =VLOOKUP(C107,Workers!B:C,2) -> 92 | E107: 46058 | F107: MIDC | G107: Helpdesk | H107: Information | I107: Priti | J107: 46058 | K107: Hindi | N107: Pending | O107: Yes | P107: Voter ID
A108: 107 | C108: Seema Shambhu Bidlan | D108: =VLOOKUP(C108,Workers!B:C,2) -> 92 | E108: 46058 | F108: MIDC | G108: Helpdesk | H108: Documents | I108: Priti | J108: 46058 | K108: Hindi | N108: Pending | O108: Yes | P108: Scholarship
A109: 108 | C109: Sushila Dharwa Pardeshi | D109: =VLOOKUP(C109,Workers!B:C,2) -> 538 | E109: 46058 | F109: Mumbai Central | G109: HR/Admin | H109: Information | I109: Priti | J109: 46058 | K109: Hindi | N109: Pending | O109: Yes | P109: Loan
A110: 109 | D110: =VLOOKUP(C110,Workers!B:C,2) -> #N/A
A111: 110 | D111: =VLOOKUP(C111,Workers!B:C,2) -> #N/A
A112: 111 | D112: =VLOOKUP(C112,Workers!B:C,2) -> #N/A
A113: 112 | D113: =VLOOKUP(C113,Workers!B:C,2) -> #N/A
A114: 113 | D114: =VLOOKUP(C114,Workers!B:C,2) -> #N/A
A115: 114 | D115: =VLOOKUP(C115,Workers!B:C,2) -> #N/A
A116: 115 | D116: =VLOOKUP(C116,Workers!B:C,2) -> #N/A
A117: 116 | D117: =VLOOKUP(C117,Workers!B:C,2) -> #N/A
A118: 117 | D118: =VLOOKUP(C118,Workers!B:C,2) -> #N/A
A119: 118 | D119: =VLOOKUP(C119,Workers!B:C,2) -> #N/A
A120: 119 | D120: =VLOOKUP(C120,Workers!B:C,2) -> #N/A
A121: 120 | D121: =VLOOKUP(C121,Workers!B:C,2) -> #N/A
... A250: 249 | D250: =VLOOKUP(C250,Workers!B:C,2) -> #N/A
D251: =VLOOKUP(C251,Workers!B:C,2) -> #N/A
D252: =VLOOKUP(C252,Workers!B:C,2) -> #N/A
D253: =VLOOKUP(C253,Workers!B:C,2) -> #N/A
...

Sheet Workers
A1: Centre | B1: Worker Name | C1: Employee Code | D1: Gender | E1: Employment type | F1: Position | I1: Missing names | J1: Case | K1: Dep | L1: Received | M1: Sent VN | N1: Code
A2: BC | B2: Aaradhana Deepak Shinde | C2: 582 | D2: F | E2: Daily | F2: Bag Checking | I2: Renu Birju pardeshi | O2: Stitching
A3: MIDC | B3: Aarti Ashok Kirkire | C3: 139 | D3: F | E3: Fixed | F3: Stitching | I3: Shajaha ansari | J3: Loan case taken and resolved | K3: Priti | L3: 46053 | M3: 46057 | N3: Hd_Q_54 | O3: staff | P3: Hd_Q_54.1
A4: MIDC | B4: Aarti Krishna Shiral | C4: 1 | D4: F | E4: Fixed | F4: Stitching
A5: BC | B5: Aarti Raju Pardeshi | C5: 589 | D5: F | E5: Fixed | F5: supervisor
A6: BC | B6: Aashish Rameshbhai Rajput | C6: 543 | D6: F | E6: per pc | F6: Stitching
A7: MIDC | B7: Aditi Vilas Kadam | C7: 2 | D7: F | E7: Fixed | F7: Panel Checking
A8: MIDC | B8: Ahmed chacha | C8: L004 | D8: M | F8: Overlock
A9: MIDC | B9: Akshta Jitendra Berde | C9: 201 | E9: Fixed | F9: Stitching
A10: BC | B10: Alka Ravi Pardeshi | C10: 502 | D10: M | E10: per pc | F10: Stitching
A11: BC | B11: Anita Gopi Pardeshi | C11: 584 | D11: M | E11: Daily | F11: Packing
A12: MIDC | B12: Anita Uttam Khandagale | C12: 5 | D12: F | E12: Fixed | F12: Thread cutting
A13: BC | B13: Anjumbanu Salman Khan | C13: 508 | D13: F | E13: per pc | F13: Stitching
A14: MIDC | B14: Ankita Laxman Sutar | C14: 4 | D14: F | E14: Fixed | F14: Stitching
A15: MIDC | B15: Ankush Kashiram Hadal | C15: 232 | D15: M | E15: Daily | F15: Logistics
A16: BC | B16: Arati Gopal Pardeshi | C16: 603 | D16: F
B17: Archita Vikas Pardeshi
A18: MIDC | B18: Arpana Alpesh Pawar | C18: 6 | D18: F | E18: Fixed | F18: Bag checking
A19: BC | B19: Arti Kisan Pardeshi | C19: 598 | D19: M | E19: Fixed | F19: supervisor
A20: MIDC | B20: Arti Sharad Mohite | C20: 7 | D20: F | E20: Fixed | F20: Stitching
B21: Asha Ganesh Pardeshi
A22: BC | B22: Asha Kishor Betwala | C22: 583 | D22: F | E22: Daily | F22: Bag Checking
A23: MIDC | B23: Ashwini Ajay Mahale | C23: 9 | D23: F | E23: Fixed | F23: Stitching
B24: Ashwini Suresh Thapad
A25: BC | B25: Ayesha Abdul Shaikh | C25: 510 | D25: F | E25: per pc | F25: Stitching
A26: BC | B26: Ayyub Mehboob Khan | C26: 507 | D26: F | E26: per pc | F26: Stitching
A27: BC | B27: Babita Birju Pardeshi | C27: MCP79
A28: BC | B28: Babita Vilas Pardeshi | C28: 562 | D28: F | E28: per pc | F28: Stitching
A29: MIDC | B29: Beby Navsha Baraf | C29: 10 | D29: F | E29: Fixed | F29: House keeping
A30: MIDC | B30: Bhanumati Nadar | C30: 234 | D30: F | E30: Daily | F30: Stitching
A31: BC | B31: Bharati Harshanand Rasal | C31: 505 | D31: F | E31: per pc | F31: Stitching
A32: MIDC | B32: Bharti Ankush Page | C32: 11 | D32: F | E32: Fixed | F32: Stitching
A33: MIDC | B33: Bharti Arvind Tokare | C33: 250 | D33: F | E33: Daily | F33: Stitching
B34: Bharti Pared
A35: BC | B35: Bharti Vikram Pardeshi | C35: 511 | D35: F | E35: per pc | F35: Stitching
A36: BC | B36: Bhavana Nitin Pardeshi | C36: 546 | D36: F | E36: per pc | F36: Stitching
A37: MIDC | B37: Chanda Devi | C37: 12 | D37: F | E37: Fixed | F37: Thread cutting
A38: MIDC | B38: Chaya Babu Kurian | C38: 13 | D38: F | E38: Fixed | F38: Thread cutting
A39: MIDC | B39: Chhaya Arun Nikam | C39: 15 | D39: F | E39: Fixed | F39: Stitching
A40: MIDC | B40: Dakshta Tejas Kadam | C40: 16 | D40: F | E40: Fixed | F40: Panel Checking
A41: BC | B41: Darshana Rishi Pardeshi | C41: 579 | D41: F | E41: Daily | F41: Bag Checking
A42: BC | B42: Deepa Vishal Pardeshi | C42: 596 | D42: F | E42: Fixed | F42: supervisor
A43: MIDC | B43: Devuni Laxmi | C43: 243
A44: MIDC | B44: Dhanlakmi Muthu Subukutti | C44: 17 | D44: F | E44: Fixed | F44: t
A45: BC | B45: Dhanraj Gudali Pardeshi | C45: 572 | D45: F | E45: Daily | F45: Bag Folding
A46: BC | B46: Dhanraj Suresh Pardeshi | C46: 512 | D46: F | E46: per pc | F46: Stitching
A47: MIDC | B47: Dipali Prakash Patil | C47: 18 | D47: F | E47: Fixed | F47: Stitching
A48: BC | B48: Divya Sagar Pali | C48: 575 | D48: F | E48: Daily | F48: Bag Folding
A49: BC | B49: Gautam Masuriyadin Pardeshi | C49: 586 | D49: M | E49: Daily | F49: Packing
A50: MIDC | B50: Gayatri Janal Made | C50: 19 | D50: F | E50: Fixed | F50: Stitching
A51: MIDC | B51: Geeta Umesh Shingde | C51: 20 | D51: F | E51: Fixed | F51: Stitching
A52: MIDC | B52: Ghulam Ahmed | C52: AN167 | D52: M
A53: MIDC | B53: Gopal Govardhan Amzare | C53: 21 | D53: M | E53: Fixed | F53: Packing
A54: MIDC | B54: Gudmesh Kumar | C54: 235 | D54: M | E54: Per PC | F54: Overlock
A55: MIDC | B55: Gunjan Ganesh Satardekar | C55: 22 | D55: F | E55: Fixed | F55: Panel Checking
A56: BC | B56: Hadiqa Jabir Shaikh | C56: 565 | D56: F | E56: per pc | F56: Stitching
A57: BC | B57: Heena Sanju Pardeshi | C57: 600 | D57: F | E57: Fixed | F57: Housekeeping
A58: MIDC | B58: Hema Laxman Tele | C58: 23 | D58: F | E58: Fixed | F58: Bag Folding
A59: BC | B59: Hemlata Avinash Pardeshi | C59: 513 | D59: F | E59: per pc | F59: Stitching
A60: MIDC | B60: Indravati Devi Sunil Kumar Jaiswal | C60: 24 | D60: F | E60: Fixed | F60: supervisor
A61: BC | B61: Iqbal Ansari | C61: 506 | D61: M | E61: per pc | F61: Stitching
A62: BC | B62: Isha Sarju Pardeshi | C62: MCP76
A63: MIDC | B63: Jamuna Ramswami Bonal | C63: 25 | D63: F | E63: Fixed | F63: Stitching
A64: BC | B64: Janki Lalji Pali | C64: 514 | D64: F | E64: per pc | F64: Stitching
A65: BC | B65: Jay Shekhar Pardeshi | C65: 599 | D65: F | E65: Fixed | F65: Housekeeping
A66: MIDC | B66: Jayanti Naresh Sawant | C66: 202 | D66: F | E66: Fixed | F66: Stitching
A67: BC | B67: Jayshree Sarju Pardeshi | C67: 515 | D67: F | E67: per pc | F67: Stitching
A68: MIDC | B68: Jayshree Sunil Dalvi | C68: 26 | D68: F | E68: Fixed | F68: Bag checking
A69: MIDC | B69: Jogendra Ramjanam Tiwari | C69: 141 | D69: M
A70: MIDC | B70: Jyostna Shankar Ullyaanand | C70: 28 | D70: F | E70: Fixed | F70: Stitching
A71: BC | B71: Jyoti Danraj Pardeshi | C71: 587 | D71: M | E71: Daily | F71: Packing
A72: MIDC | B72: Jyoti Dasharath Madhe | C72: 27 | D72: F | E72: Fixed | F72: Bag Folding
A73: MIDC | B73: Jyoti Shivram Sutar | C73: 218 | D73: F
A74: MIDC | B74: Jyotsana Datta Valvi | C74: 251 | D74: F
A75: MIDC | B75: Kalaiyrashi Murgeshan Nadar | C75: 29 | D75: F | E75: Fixed | F75: Stitching
A76: BC | B76: Kalpana Kiran Shinde | C76: 542 | D76: F | E76: per pc | F76: Stitching
A77: MIDC | B77: Kalpana Mahesh Chaudhary | C77: 30 | D77: F | E77: Fixed | F77: Stitching
A78: MIDC | B78: Kalpana Nandu Lotade | C78: 220 | D78: F | E78: Daily | F78: Stitching
A79: MIDC | B79: Kalpana Sandeep Patil | C79: 31 | D79: F | E79: Fixed | F79: Stitching
A80: BC | B80: Kalpana Sunny Pardeshi | C80: 556 | D80: F | E80: per pc | F80: Stitching
A81: BC | B81: Kanchan Kishor Pardeshi | C81: 580 | D81: F | E81: Daily | F81: Bag Folding
A82: MIDC | B82: Karuna Krishna Gawade | C82: 32 | D82: F | E82: Fixed | F82: Stitching
A83: BC | B83: Kaveri L Ramteke | C83: 574 | D83: F | E83: Daily | F83: Thread cutting
A84: MIDC | B84: Kavita Santosh Mhatre | C84: 33 | D84: F | E84: Fixed | F84: Stitching
A85: BC | B85: Kishori Kishor Pandav | C85: 501 | D85: F | E85: per pc | F85: Stitching
A86: BC | B86: Kripa Sarju Pardeshi | C86: MCP77
A87: MIDC | B87: Krupali Ravindra Patil | C87: 134 | D87: F | E87: Fixed | F87: Stitching
A88: MIDC | B88: Krutika Kishore Saware | C88: 35 | D88: F | E88: Fixed | F88: Stitching
A89: MIDC | B89: Kunda Kamlakar Bombare | C89: 132 | D89: F | E89: Fixed | F89: Stitching
A90: MIDC | B90: Kuppu Manohar | C90: 36 | D90: F | E90: Fixed | F90: Stitching
A91: BC | B91: Lalita Shekhar Mathur | C91: 519 | D91: F | E91: per pc | F91: Stitching
A92: MIDC | B92: Lata Bapu Patil | C92: 37 | D92: F | E92: Fixed | F92: Stitching
A93: MIDC | B93: Laxmi Shankar Dubbaka | C93: 38 | D93: F | E93: Fixed | F93: Stitching
A94: MIDC | B94: Leena Khandu Garud | C94: 39 | D94: F | E94: Fixed | F94: Stitching
A95: MIDC | B95: Lueeja Philips Dsouza | C95: 40 | D95: F | E95: Fixed | F95: Stitching
A96: BC | B96: Madhu Ganesh Pardeshi | C96: 585 | D96: M | E96: Daily | F96: Packing
A97: BC | B97: Madhuri Shesnarayan Tiwari | C97: 552 | D97: F | E97: per pc | F97: Stitching
A98: BC | B98: Madhuri Sonu Pardeshi | C98: 567 | D98: F | E98: per pc | F98: Stitching
... A100: MIDC | B100: Mahesh Kashiram Shirvalker | C100: 42 | D100: M | E100: Per PC | F100: Overlock
A101: MIDC | B101: Mamta Olambe | C101: 240 | D101: F | E101: Daily
...

Sheet Ai Platform
A1: Sr No. | B1: Name
A2: 1 | B2: Telnyx – Voice AI Agents
A3: 2 | B3: VocalRAG – Voice-First Knowledge AI Platform
A4: 3 | B4: Kriatix
A5: 4 | B5: Ameyo Voice Bot
A6: 5 | B6: byVoice
A7: 6 | B7: Amazon Lex
A8: 7 | B8: Convozen AI
A9: 8 | B9: Emergent
A10: 9 | B10: Open-Source (Intervo/VoxArena)
A11: 10 | B11: Salesforce Agentforce 360 / Voice
A12: 11 | B12: Google Dialogflow CX | C12: best fit for guard requirement
A13: 12 | B13: Amazon Connect + Lex | C13: best fit for guard requirement
A14: 13 | B14: Kore.ai | C14: best fit for guard requirement
A15: 14 | B15: Eleven lab - New version | C15: For whatsapp connection
A16: 15 | B16: GPT agent
A17: 16 | B17: VoiceGenie
